{"translate":{"translatedLabel":{"paidLabel":"Pagita","unpaidLabel":"Nepagita","fulfilledLabel":"Plenum","unfulfilledLabel":"Neplenum","refundedLabel":"Repagita","invoiceTitle":"Fakturo","packingSlipTitle":"Pakfolieto","refundTitle":"Repago","paymentInfo":{"title":"Pagaj Informoj"},"shippingAddress":{"title":"Ekspedanta Adreso"},"lineItems":{"hsCodeLabel":"HS Kodo","vendorLabel":"Vendisto","weightLabel":"Pezo","totalLabel":"Sumo","unitPriceLabel":"Unu-prezo","priceLabel":"Prezo","priceExcludeTaxLabel":"Prezo sen Imposto","taxLabel":"Imposto","taxAmountLabel":"Impostkvanto","discountLabel":"Rabato","fulfillmentLocationLabel":"Plena Loko","qtyLabel":"Kvanto","skuLabel":"SKU","variantLabel":"Varianto"},"totalQuantityLabel":"Totala kvanto","totalWeightLabel":"Totala pezo","itemsLabel":"Eroj","orderNumberText":"Mendnumero","invoiceNumberText":"Faktura Numero","refundNumberText":"Repaga Numero","packingSlipNumberText":"Pakfolieta Numero","poNumberText":"PO Numero","amountText":"Sumo","notesText":"Notoj","orderDateText":"Menddato","dueDateText":"Pagenda Dato","orderOverviewText":"Menda Superrigardo","customerSectionText":"Kliento","subtotalText":"Subtotalo","discountText":"Rabato","shippingText":"Ekspedado","totalExcludeTaxText":"Totalo sen imposto","taxText":"Imposto","grandTotalText":"Granda Entuto","refundedText":"Repagita","netPaymentText":"Neta pago","balanceText":"Bilanco","paidByCustomerText":"Pagita de Kliento","thankYouText":"Dankon pro via aĉeto","additionalFooterNotesDetail":"Se vi havas demandojn, bonvolu kontakti nin."}}}