{"translate":{"translatedLabel":{"paidLabel":"Makstud","unpaidLabel":"Maksmata","fulfilledLabel":"Täidetud","unfulfilledLabel":"Täitmata","refundedLabel":"Tagastatud","invoiceTitle":"Arve","packingSlipTitle":"Pakkimisleht","refundTitle":"Tagasimakse","paymentInfo":{"title":"Makseinfo"},"shippingAddress":{"title":"Saateaadress"},"lineItems":{"hsCodeLabel":"HS kood","vendorLabel":"Müüja","weightLabel":"Kaal","totalLabel":"Kokku","unitPriceLabel":"Ühiku hind","priceExcludeTaxLabel":"Hind ilma maksudeta","taxLabel":"Maks","taxAmountLabel":"Maksu summa","discountLabel":"Allahindlus","fulfillmentLocationLabel":"Täitmise asukoht","qtyLabel":"Kogus","skuLabel":"Laoseisuüksus","variantLabel":"Variant"},"totalQuantityLabel":"Kogusumma","totalWeightLabel":"Kogukaal","itemsLabel":"Esemed","orderNumberText":"Tellimuse number","invoiceNumberText":"Arve number","refundNumberText":"Tagasimakse number","packingSlipNumberText":"Pakkimislehe number","poNumberText":"Ostutellimuse number","amountText":"Summa","notesText":"Märkmed","orderDateText":"Tellimuse kuupäev","dueDateText":"Tähtaeg","orderOverviewText":"Tellimuse ülevaade","customerSectionText":"Klient","subtotalText":"Vahesumma","discountText":"Allahindlus","shippingText":"Saatmine","totalExcludeTaxText":"Kokku ilma maksudeta","taxText":"Maks","grandTotalText":"Lõppsumma","refundedText":"Tagastatud","netPaymentText":"Netomakse","balanceText":"Saldo","paidByCustomerText":"Maksja klient","thankYouText":"Täname ostu eest","additionalFooterNotesDetail":"Kui teil on küsimusi, võtke meiega ühendust."}}}