{"translate":{"translatedLabel":{"paidLabel":"Erchit","unpaidLabel":"Neu erch","fulfilledLabel":"Creaght","unfulfilledLabel":"Neu chreaght","refundedLabel":"Errooit reesht","invoiceTitle":"Aggair","packingSlipTitle":"Shlieh cheh","refundTitle":"Reeshtys","paymentInfo":{"title":"Fysheeaght Faie"},"shippingAddress":{"title":"Fysheeaght Ghaaueys"},"lineItems":{"hsCodeLabel":"Coadeeaght HS","vendorLabel":"Dooar","weightLabel":"Megh","totalLabel":"Eroorey","unitPriceLabel":"Eroorey yn Unnane","priceLabel":"Eroorey","priceExcludeTaxLabel":"Eroorey neu-higgyltaxee","taxLabel":"Higgyltaxee","taxAmountLabel":"Mee-higgyltaxee","discountLabel":"Lhiastyn","fulfillmentLocationLabel":"Boayl Fysheeaght","qtyLabel":"Cooish","skuLabel":"SKU","variantLabel":"Collagh"},"totalQuantityLabel":"Eroorey cooish","totalWeightLabel":"Eroorey megh","itemsLabel":"Reddyn","orderNumberText":"Shliaue Erree","invoiceNumberText":"Shliaue Aggair","refundNumberText":"Shliaue Reeshtys","packingSlipNumberText":"Shliaue Shlieh Cheh","poNumberText":"Shliaue PO","amountText":"Meech","notesText":"Noteyn","orderDateText":"Date Erree","dueDateText":"Date ree","orderOverviewText":"Seihll Erree","customerSectionText":"Cliant","subtotalText":"Fo Eayst","discountText":"Lhiastynys","shippingText":"Gaaueys","totalExcludeTaxText":"Eroorey neu-higgyltaxee","taxText":"Higgyltaxee","grandTotalText":"Eroorey mooar","refundedText":"Errooit reesht","netPaymentText":"Erchyn glan","balanceText":"Mease","paidByCustomerText":"Erchit ec y chliant","thankYouText":"Moollee share son dty cheayl","additionalFooterNotesDetail":"Myr ta mee er ny yantyn, cur fys ta mee er cooish."}}}