{"translate":{"translatedLabel":{"paidLabel":"Apmokėta","unpaidLabel":"Neapmokėta","fulfilledLabel":"Įvykdyta","unfulfilledLabel":"Neįvykdyta","refundedLabel":"Grąžinta","invoiceTitle":"Sąskaita faktūra","packingSlipTitle":"Pakavimo lapelis","refundTitle":"Grąžinimas","paymentInfo":{"title":"Mokėjimo informacija"},"shippingAddress":{"title":"Pristatymo adresas"},"lineItems":{"hsCodeLabel":"HS kodas","vendorLabel":"Pardavėjas","weightLabel":"Svoris","totalLabel":"Iš viso","unitPriceLabel":"Vieneto kaina","priceLabel":"Kaina","priceExcludeTaxLabel":"Kaina be mokesčių","taxLabel":"Mokestis","taxAmountLabel":"Mokesčio suma","discountLabel":"Nuolaida","fulfillmentLocationLabel":"Įvykdymo vieta","qtyLabel":"Kiekis","skuLabel":"SKU","variantLabel":"Variantas"},"totalQuantityLabel":"Bendra suma","totalWeightLabel":"Bendras svoris","itemsLabel":"Prekės","orderNumberText":"Užsakymo numeris","invoiceNumberText":"Sąskaitos faktūros numeris","refundNumberText":"Grąžinimo numeris","packingSlipNumberText":"Pakavimo lapelio numeris","poNumberText":"Pirkimo užsakymo numeris","amountText":"Suma","notesText":"Pastabos","orderDateText":"Užsakymo data","dueDateText":"Mokėjimo data","orderOverviewText":"Užsakymo apžvalga","customerSectionText":"Klientas","subtotalText":"Tarpinė suma","discountText":"Nuolaida","shippingText":"Pristatymas","totalExcludeTaxText":"Bendra suma be mokesčių","taxText":"Mokestis","grandTotalText":"Bendra visų suma","refundedText":"Grąžinta","netPaymentText":"Grynasis mokėjimas","balanceText":"Balansas","paidByCustomerText":"Apmokėta kliento","thankYouText":"Dėkojame už pirkinį","additionalFooterNotesDetail":"Jei turite klausimų, prašome susisiekti."}}}